dpt_rp1_py-0.1.19.dist-info/licenses/LICENSE
dptrp1/__init__.py
dptrp1/dptrp1.py
dptrp1/pyDH.py
dptrp1/cli/__init__.py
dptrp1/cli/dptmount.py
dptrp1/cli/dptrp1.py
dpt_rp1_py-0.1.19.dist-info/METADATA
dpt_rp1_py-0.1.19.dist-info/WHEEL
dpt_rp1_py-0.1.19.dist-info/entry_points.txt
dpt_rp1_py-0.1.19.dist-info/namespace_packages.txt
dpt_rp1_py-0.1.19.dist-info/top_level.txt
dpt_rp1_py-0.1.19.dist-info/RECORD
