Metadata-Version: 2.4
Name: dpt-rp1-py
Version: 0.1.19
Summary: Python package to manage a Sony DPT-RP1
Author: Jan-Gerd Tenberge, Cuihtlauac Alvarado, Juan Grigera, Yunjae Lee, Kazuhiko Sakaguchi, Yanzi Zhu, Sreepathi Pai, Jochen Schroeder, Alexander Fuchs, Xiang Ji, Håkon J. D. Johnsen
Author-email: jan-gerd.tenberge@uni-muenster.de, cuihtlauac.alvarado@orange.com, juan@grigera.com.ar, lyj7694@gmail.com, pi8027@gmail.com, zhuyanzi@gmail.com, sree314@gmail.com, jochen.schroeder@chalmers.se, alex.fu27@gmail.com, hi@xiangji.me, hakon.j.d.johnsen@ntnu.no
License: MIT
Classifier: Development Status :: 3 - Alpha
Classifier: Programming Language :: Python :: 3
License-File: LICENSE
Requires-Dist: httpsig>=1.1.2
Requires-Dist: requests>=2.18.4
Requires-Dist: pbkdf2>=1.3
Requires-Dist: urllib3>=1.22
Requires-Dist: pyyaml
Requires-Dist: anytree
Requires-Dist: fusepy
Requires-Dist: zeroconf>=0.29.0
Requires-Dist: tqdm
Requires-Dist: setuptools
Dynamic: author
Dynamic: author-email
Dynamic: classifier
Dynamic: description
Dynamic: description-content-type
Dynamic: keywords
Dynamic: license
Dynamic: license-file
Dynamic: requires-dist
Dynamic: summary
